silvergram/__init__.py
silvergram/__main__.py
silvergram/silvergram.py
silvergram/exceptions/__init__.py
silvergram/exceptions/no_such_step.py
silvergram/types/__init__.py
silvergram/types/inherited_step.py
silvergram-0.0.4.dist-info/LICENSE
silvergram-0.0.4.dist-info/METADATA
silvergram-0.0.4.dist-info/WHEEL
silvergram-0.0.4.dist-info/top_level.txt
silvergram-0.0.4.dist-info/RECORD
