Metadata-Version: 2.1
Name: silvergram
Version: 0.0.4
Summary: A convenient shell for the Aiogram library
Home-page: https://github.com/SilverBullet-Technologies/silvergram
Author: SilverBullet Technologies
Author-email: tech.silver.bullet@gmail.com
License-File: LICENSE
Requires-Dist: aiogram >=3.4.1
